example_project/src/user_project_example.v
`default_nettype none

module user_project_example(
`ifdef USE_POWER_PINS
	inout wire VSS,
	inout wire VDD,
`endif
	input clk_i,
	input rst_n, //Active low
	
	//These all map to the 36 user-assignable IO pads
	output [35:0] io_out,
	output [35:0] io_oeb, //Active-low output enable (0 = output, 1 = input). These must ALL be assigned a value, even for pins that are fixed inputs/outputs
	input [35:0] io_in
);

wire OE  = !io_in[34];
wire WEb = io_in[35];

assign io_oeb = {2'b11, {34{!OE}}};

reg [33:0] count;
assign io_out = {2'b00, count};

always @(posedge clk_i) begin
	if(!rst_n) begin
		count <= 0;
	end else begin
		count <= count + 1;
		if(!WEb) count <= io_in[33:0];
	end
end

endmodule

example_project/src/fpga_wrapper.v
`default_nettype none

/*
 * Wrapper to let you try things on an FPGA - not part of the chip flow
 */

module fpga_wrapper(
	input clk_i,
	input rst_n,
	inout [35:0] gpio
);

wire [35:0] io_out;
wire [35:0] io_in = gpio;
wire [35:0] io_oeb;

assign gpio[0] = io_oeb[0] ? 1'bz : io_out[0];
assign gpio[1] = io_oeb[1] ? 1'bz : io_out[1];
assign gpio[2] = io_oeb[2] ? 1'bz : io_out[2];
assign gpio[3] = io_oeb[3] ? 1'bz : io_out[3];
assign gpio[4] = io_oeb[4] ? 1'bz : io_out[4];
assign gpio[5] = io_oeb[5] ? 1'bz : io_out[5];
assign gpio[6] = io_oeb[6] ? 1'bz : io_out[6];
assign gpio[7] = io_oeb[7] ? 1'bz : io_out[7];
assign gpio[8] = io_oeb[8] ? 1'bz : io_out[8];
assign gpio[9] = io_oeb[9] ? 1'bz : io_out[9];
assign gpio[10] = io_oeb[10] ? 1'bz : io_out[10];
assign gpio[11] = io_oeb[11] ? 1'bz : io_out[11];
assign gpio[12] = io_oeb[12] ? 1'bz : io_out[12];
assign gpio[13] = io_oeb[13] ? 1'bz : io_out[13];
assign gpio[14] = io_oeb[14] ? 1'bz : io_out[14];
assign gpio[15] = io_oeb[15] ? 1'bz : io_out[15];
assign gpio[16] = io_oeb[16] ? 1'bz : io_out[16];
assign gpio[17] = io_oeb[17] ? 1'bz : io_out[17];
assign gpio[18] = io_oeb[18] ? 1'bz : io_out[18];
assign gpio[19] = io_oeb[19] ? 1'bz : io_out[19];
assign gpio[20] = io_oeb[20] ? 1'bz : io_out[20];
assign gpio[21] = io_oeb[21] ? 1'bz : io_out[21];
assign gpio[22] = io_oeb[22] ? 1'bz : io_out[22];
assign gpio[23] = io_oeb[23] ? 1'bz : io_out[23];
assign gpio[24] = io_oeb[24] ? 1'bz : io_out[24];
assign gpio[25] = io_oeb[25] ? 1'bz : io_out[25];
assign gpio[26] = io_oeb[26] ? 1'bz : io_out[26];
assign gpio[27] = io_oeb[27] ? 1'bz : io_out[27];
assign gpio[28] = io_oeb[28] ? 1'bz : io_out[28];
assign gpio[29] = io_oeb[29] ? 1'bz : io_out[29];
assign gpio[30] = io_oeb[30] ? 1'bz : io_out[30];
assign gpio[31] = io_oeb[31] ? 1'bz : io_out[31];
assign gpio[32] = io_oeb[32] ? 1'bz : io_out[32];
assign gpio[33] = io_oeb[33] ? 1'bz : io_out[33];
assign gpio[34] = io_oeb[34] ? 1'bz : io_out[34];
assign gpio[35] = io_oeb[35] ? 1'bz : io_out[35];

user_project_example mprj(
	.clk_i(clk_i),
	.rst_n(rst_n),
	.io_out(io_out),
	.io_in(io_in),
	.io_oeb(io_oeb)
);

endmodule

example_project/dv/tb.v
`default_nettype none

`timescale 1ns/1ps

module tb(
	input clk_i,
	input rst_n,
	input oeb,
	input web,
	input [33:0] count_set,
	output [33:0] count
);

initial begin
	$dumpfile ("tb.vcd");
	$dumpvars (0, tb);
	#1;
end

wire [35:0] gpio;
assign gpio[35] = web;
assign gpio[34] = oeb;
assign gpio[33:0] = web ? 34'hzzzzzzzzz : count_set;
assign count = gpio[33:0];

fpga_wrapper dut(
	.clk_i(clk_i),
	.rst_n(rst_n),
	.gpio(gpio)
);

endmodule

example_project/dv/tb.vcd
$date
	Tue Sep 16 16:59:46 2025
$end
$version
	Icarus Verilog
$end
$timescale
	1ps
$end
$scope module tb $end
$var wire 1 ! clk_i $end
$var wire 34 " count_set [33:0] $end
$var wire 36 # gpio [35:0] $end
$var wire 1 $ oeb $end
$var wire 1 % rst_n $end
$var wire 1 & web $end
$var wire 34 ' count [33:0] $end
$scope module dut $end
$var wire 1 ! clk_i $end
$var wire 36 ( gpio [35:0] $end
$var wire 36 ) io_in [35:0] $end
$var wire 1 % rst_n $end
$var wire 36 * io_out [35:0] $end
$var wire 36 + io_oeb [35:0] $end
$scope module mprj $end
$var wire 1 ! clk_i $end
$var wire 36 , io_in [35:0] $end
$var wire 1 % rst_n $end
$var wire 36 - io_out [35:0] $end
$var wire 36 . io_oeb [35:0] $end
$var wire 1 / WEb $end
$var wire 1 0 OE $end
$var reg 34 1 count [33:0] $end
$upscope $end
$upscope $end
$upscope $end
$enddefinitions $end
$comment Show the parameter values. $end
$dumpall
$end
#0
$dumpvars
b0 1
10
1/
b110000000000000000000000000000000000 .
b0 -
b100000000000000000000000000000000000 ,
b110000000000000000000000000000000000 +
b0 *
b100000000000000000000000000000000000 )
b100000000000000000000000000000000000 (
b0 '
1&
0%
0$
b100000000000000000000000000000000000 #
bz "
1!
$end
#20000
0!
#40000
1!
#60000
0!
#80000
1!
#100000
0!
#120000
1!
#140000
0!
#160000
1!
#180000
0!
#200000
1!
#220000
0!
#240000
1!
#260000
0!
#280000
1!
#300000
0!
#320000
1!
#340000
0!
#360000
1%
1!
#380000
0!
#400000
b1 '
b100000000000000000000000000000000001 )
b100000000000000000000000000000000001 ,
b100000000000000000000000000000000001 #
b100000000000000000000000000000000001 (
b1 *
b1 -
b1 1
1!
#420000
0!
#440000
b10 '
b100000000000000000000000000000000010 )
b100000000000000000000000000000000010 ,
b100000000000000000000000000000000010 #
b100000000000000000000000000000000010 (
b10 *
b10 -
b10 1
1!
#460000
0!
#480000
b11 '
b100000000000000000000000000000000011 )
b100000000000000000000000000000000011 ,
b100000000000000000000000000000000011 #
b100000000000000000000000000000000011 (
b11 *
b11 -
b11 1
1!
#500000
0!
#520000
b100 '
b100000000000000000000000000000000100 )
b100000000000000000000000000000000100 ,
b100000000000000000000000000000000100 #
b100000000000000000000000000000000100 (
b100 *
b100 -
b100 1
1!
#540000
0!
#560000
b101 '
b100000000000000000000000000000000101 )
b100000000000000000000000000000000101 ,
b100000000000000000000000000000000101 #
b100000000000000000000000000000000101 (
b101 *
b101 -
b101 1
1!
#580000
0!
#600000
b110 '
b100000000000000000000000000000000110 )
b100000000000000000000000000000000110 ,
b100000000000000000000000000000000110 #
b100000000000000000000000000000000110 (
b110 *
b110 -
b110 1
1!
#620000
0!
#640000
b111 '
b100000000000000000000000000000000111 )
b100000000000000000000000000000000111 ,
b100000000000000000000000000000000111 #
b100000000000000000000000000000000111 (
b111 *
b111 -
b111 1
1!
#660000
0!
#680000
b1000 '
b100000000000000000000000000000001000 )
b100000000000000000000000000000001000 ,
b100000000000000000000000000000001000 #
b100000000000000000000000000000001000 (
b1000 *
b1000 -
b1000 1
1!
#700000
0!
#720000
b1001 '
b100000000000000000000000000000001001 )
b100000000000000000000000000000001001 ,
b100000000000000000000000000000001001 #
b100000000000000000000000000000001001 (
b1001 *
b1001 -
b1001 1
1!
#740000
0!
#760000
b1010 '
b100000000000000000000000000000001010 )
b100000000000000000000000000000001010 ,
b100000000000000000000000000000001010 #
b100000000000000000000000000000001010 (
b1010 *
b1010 -
b1010 1
1!
#780000
0!
#800000
b1011 '
b100000000000000000000000000000001011 )
b100000000000000000000000000000001011 ,
b100000000000000000000000000000001011 #
b100000000000000000000000000000001011 (
b1011 *
b1011 -
b1011 1
1!
#820000
0!
#840000
b1100 '
b100000000000000000000000000000001100 )
b100000000000000000000000000000001100 ,
b100000000000000000000000000000001100 #
b100000000000000000000000000000001100 (
b1100 *
b1100 -
b1100 1
1!
#860000
0!
#880000
b1101 '
b100000000000000000000000000000001101 )
b100000000000000000000000000000001101 ,
b100000000000000000000000000000001101 #
b100000000000000000000000000000001101 (
b1101 *
b1101 -
b1101 1
1!
#900000
0!
#920000
b1110 '
b100000000000000000000000000000001110 )
b100000000000000000000000000000001110 ,
b100000000000000000000000000000001110 #
b100000000000000000000000000000001110 (
b1110 *
b1110 -
b1110 1
1!
#940000
0!
#960000
b1111 '
b100000000000000000000000000000001111 )
b100000000000000000000000000000001111 ,
b100000000000000000000000000000001111 #
b100000000000000000000000000000001111 (
b1111 *
b1111 -
b1111 1
1!
#980000
0!
#1000000
b10000 '
b100000000000000000000000000000010000 )
b100000000000000000000000000000010000 ,
b100000000000000000000000000000010000 #
b100000000000000000000000000000010000 (
b10000 *
b10000 -
b10000 1
1!
#1020000
0!
#1040000
b10001 '
b100000000000000000000000000000010001 )
b100000000000000000000000000000010001 ,
b100000000000000000000000000000010001 #
b100000000000000000000000000000010001 (
b10001 *
b10001 -
b10001 1
1!
#1060000
0!
#1080000
b10010 '
b100000000000000000000000000000010010 )
b100000000000000000000000000000010010 ,
b100000000000000000000000000000010010 #
b100000000000000000000000000000010010 (
b10010 *
b10010 -
b10010 1
1!
#1100000
0!
#1120000
b10011 '
b100000000000000000000000000000010011 )
b100000000000000000000000000000010011 ,
b100000000000000000000000000000010011 #
b100000000000000000000000000000010011 (
b10011 *
b10011 -
b10011 1
1!
#1140000
0!
#1160000
b10100 '
b100000000000000000000000000000010100 )
b100000000000000000000000000000010100 ,
b100000000000000000000000000000010100 #
b100000000000000000000000000000010100 (
b10100 *
b10100 -
b10100 1
1!
#1180000
0!
#1200000
b10101 '
b100000000000000000000000000000010101 )
b100000000000000000000000000000010101 ,
b100000000000000000000000000000010101 #
b100000000000000000000000000000010101 (
b10101 *
b10101 -
b10101 1
1!
#1220000
0!
#1240000
b10110 '
b100000000000000000000000000000010110 )
b100000000000000000000000000000010110 ,
b100000000000000000000000000000010110 #
b100000000000000000000000000000010110 (
b10110 *
b10110 -
b10110 1
1!
#1260000
0!
#1280000
b10111 '
b100000000000000000000000000000010111 )
b100000000000000000000000000000010111 ,
b100000000000000000000000000000010111 #
b100000000000000000000000000000010111 (
b10111 *
b10111 -
b10111 1
1!
#1300000
0!
#1320000
b11000 '
b100000000000000000000000000000011000 )
b100000000000000000000000000000011000 ,
b100000000000000000000000000000011000 #
b100000000000000000000000000000011000 (
b11000 *
b11000 -
b11000 1
1!
#1340000
0!
#1360000
b11001 '
b100000000000000000000000000000011001 )
b100000000000000000000000000000011001 ,
b100000000000000000000000000000011001 #
b100000000000000000000000000000011001 (
b11001 *
b11001 -
b11001 1
1!
#1380000
0!
#1400000
b11010 '
b100000000000000000000000000000011010 )
b100000000000000000000000000000011010 ,
b100000000000000000000000000000011010 #
b100000000000000000000000000000011010 (
b11010 *
b11010 -
b11010 1
1!
#1420000
0!
#1440000
b11011 '
b100000000000000000000000000000011011 )
b100000000000000000000000000000011011 ,
b100000000000000000000000000000011011 #
b100000000000000000000000000000011011 (
b11011 *
b11011 -
b11011 1
1!
#1460000
0!
#1480000
b11100 '
b100000000000000000000000000000011100 )
b100000000000000000000000000000011100 ,
b100000000000000000000000000000011100 #
b100000000000000000000000000000011100 (
b11100 *
b11100 -
b11100 1
1!
#1500000
0!
#1520000
b11101 '
b100000000000000000000000000000011101 )
b100000000000000000000000000000011101 ,
b100000000000000000000000000000011101 #
b100000000000000000000000000000011101 (
b11101 *
b11101 -
b11101 1
1!
#1540000
0!
#1560000
b11110 '
b100000000000000000000000000000011110 )
b100000000000000000000000000000011110 ,
b100000000000000000000000000000011110 #
b100000000000000000000000000000011110 (
b11110 *
b11110 -
b11110 1
1!
#1580000
0!
#1600000
b11111 '
b100000000000000000000000000000011111 )
b100000000000000000000000000000011111 ,
b100000000000000000000000000000011111 #
b100000000000000000000000000000011111 (
b11111 *
b11111 -
b11111 1
1!
#1620000
0!
#1640000
b100000 '
b100000000000000000000000000000100000 )
b100000000000000000000000000000100000 ,
b100000000000000000000000000000100000 #
b100000000000000000000000000000100000 (
b100000 *
b100000 -
b100000 1
1!
#1660000
0!
#1680000
b100001 '
b100000000000000000000000000000100001 )
b100000000000000000000000000000100001 ,
b100000000000000000000000000000100001 #
b100000000000000000000000000000100001 (
b100001 *
b100001 -
b100001 1
1!
#1700000
0!
#1720000
b100010 '
b100000000000000000000000000000100010 )
b100000000000000000000000000000100010 ,
b100000000000000000000000000000100010 #
b100000000000000000000000000000100010 (
b100010 *
b100010 -
b100010 1
1!
#1740000
0!
#1760000
b100011 '
b100000000000000000000000000000100011 )
b100000000000000000000000000000100011 ,
b100000000000000000000000000000100011 #
b100000000000000000000000000000100011 (
b100011 *
b100011 -
b100011 1
1!
#1780000
0!
#1800000
b100100 '
b100000000000000000000000000000100100 )
b100000000000000000000000000000100100 ,
b100000000000000000000000000000100100 #
b100000000000000000000000000000100100 (
b100100 *
b100100 -
b100100 1
1!
#1820000
0!
#1840000
b100101 '
b100000000000000000000000000000100101 )
b100000000000000000000000000000100101 ,
b100000000000000000000000000000100101 #
b100000000000000000000000000000100101 (
b100101 *
b100101 -
b100101 1
1!
#1860000
0!
#1880000
b100110 '
b100000000000000000000000000000100110 )
b100000000000000000000000000000100110 ,
b100000000000000000000000000000100110 #
b100000000000000000000000000000100110 (
b100110 *
b100110 -
b100110 1
1!
#1900000
0!
#1920000
b100111 '
b100000000000000000000000000000100111 )
b100000000000000000000000000000100111 ,
b100000000000000000000000000000100111 #
b100000000000000000000000000000100111 (
b100111 *
b100111 -
b100111 1
1!
#1940000
0!
#1960000
b101000 '
b100000000000000000000000000000101000 )
b100000000000000000000000000000101000 ,
b100000000000000000000000000000101000 #
b100000000000000000000000000000101000 (
b101000 *
b101000 -
b101000 1
1!
#1980000
0!
#2000000
b101001 '
b100000000000000000000000000000101001 )
b100000000000000000000000000000101001 ,
b100000000000000000000000000000101001 #
b100000000000000000000000000000101001 (
b101001 *
b101001 -
b101001 1
1!
#2020000
0!
#2040000
b101010 '
b100000000000000000000000000000101010 )
b100000000000000000000000000000101010 ,
b100000000000000000000000000000101010 #
b100000000000000000000000000000101010 (
b101010 *
b101010 -
b101010 1
1!
#2060000
0!
#2080000
b101011 '
b100000000000000000000000000000101011 )
b100000000000000000000000000000101011 ,
b100000000000000000000000000000101011 #
b100000000000000000000000000000101011 (
b101011 *
b101011 -
b101011 1
1!
#2100000
0!
#2120000
b101100 '
b100000000000000000000000000000101100 )
b100000000000000000000000000000101100 ,
b100000000000000000000000000000101100 #
b100000000000000000000000000000101100 (
b101100 *
b101100 -
b101100 1
1!
#2140000
0!
#2160000
b101101 '
b100000000000000000000000000000101101 )
b100000000000000000000000000000101101 ,
b100000000000000000000000000000101101 #
b100000000000000000000000000000101101 (
b101101 *
b101101 -
b101101 1
1!
#2180000
0!
#2200000
b101110 '
b100000000000000000000000000000101110 )
b100000000000000000000000000000101110 ,
b100000000000000000000000000000101110 #
b100000000000000000000000000000101110 (
b101110 *
b101110 -
b101110 1
1!
#2220000
0!
#2240000
b101111 '
b100000000000000000000000000000101111 )
b100000000000000000000000000000101111 ,
b100000000000000000000000000000101111 #
b100000000000000000000000000000101111 (
b101111 *
b101111 -
b101111 1
1!
#2260000
0!
#2280000
b110000 '
b100000000000000000000000000000110000 )
b100000000000000000000000000000110000 ,
b100000000000000000000000000000110000 #
b100000000000000000000000000000110000 (
b110000 *
b110000 -
b110000 1
1!
#2300000
0!
#2320000
b110001 '
b100000000000000000000000000000110001 )
b100000000000000000000000000000110001 ,
b100000000000000000000000000000110001 #
b100000000000000000000000000000110001 (
b110001 *
b110001 -
b110001 1
1!
#2340000
0!
#2360000
b110010 '
b100000000000000000000000000000110010 )
b100000000000000000000000000000110010 ,
b100000000000000000000000000000110010 #
b100000000000000000000000000000110010 (
b110010 *
b110010 -
b110010 1
1!
#2380000
0!
#2400000
b110011 '
b100000000000000000000000000000110011 )
b100000000000000000000000000000110011 ,
b100000000000000000000000000000110011 #
b100000000000000000000000000000110011 (
b110011 *
b110011 -
b110011 1
1!
#2420000
0!
#2440000
b110100 '
b100000000000000000000000000000110100 )
b100000000000000000000000000000110100 ,
b100000000000000000000000000000110100 #
b100000000000000000000000000000110100 (
b110100 *
b110100 -
b110100 1
1!
#2460000
0!
#2480000
b110101 '
b100000000000000000000000000000110101 )
b100000000000000000000000000000110101 ,
b100000000000000000000000000000110101 #
b100000000000000000000000000000110101 (
b110101 *
b110101 -
b110101 1
1!
#2500000
0!
#2520000
b110110 '
b100000000000000000000000000000110110 )
b100000000000000000000000000000110110 ,
b100000000000000000000000000000110110 #
b100000000000000000000000000000110110 (
b110110 *
b110110 -
b110110 1
1!
#2540000
0!
#2560000
b110111 '
b100000000000000000000000000000110111 )
b100000000000000000000000000000110111 ,
b100000000000000000000000000000110111 #
b100000000000000000000000000000110111 (
b110111 *
b110111 -
b110111 1
1!
#2580000
0!
#2600000
b111000 '
b100000000000000000000000000000111000 )
b100000000000000000000000000000111000 ,
b100000000000000000000000000000111000 #
b100000000000000000000000000000111000 (
b111000 *
b111000 -
b111000 1
1!
#2620000
0!
#2640000
b111001 '
b100000000000000000000000000000111001 )
b100000000000000000000000000000111001 ,
b100000000000000000000000000000111001 #
b100000000000000000000000000000111001 (
b111001 *
b111001 -
b111001 1
1!
#2660000
0!
#2680000
b111010 '
b100000000000000000000000000000111010 )
b100000000000000000000000000000111010 ,
b100000000000000000000000000000111010 #
b100000000000000000000000000000111010 (
b111010 *
b111010 -
b111010 1
1!
#2700000
0!
#2720000
b111011 '
b100000000000000000000000000000111011 )
b100000000000000000000000000000111011 ,
b100000000000000000000000000000111011 #
b100000000000000000000000000000111011 (
b111011 *
b111011 -
b111011 1
1!
#2740000
0!
#2760000
b111100 '
b100000000000000000000000000000111100 )
b100000000000000000000000000000111100 ,
b100000000000000000000000000000111100 #
b100000000000000000000000000000111100 (
b111100 *
b111100 -
b111100 1
1!
#2780000
0!
#2800000
b111101 '
b100000000000000000000000000000111101 )
b100000000000000000000000000000111101 ,
b100000000000000000000000000000111101 #
b100000000000000000000000000000111101 (
b111101 *
b111101 -
b111101 1
1!
#2820000
0!
#2840000
b111110 '
b100000000000000000000000000000111110 )
b100000000000000000000000000000111110 ,
b100000000000000000000000000000111110 #
b100000000000000000000000000000111110 (
b111110 *
b111110 -
b111110 1
1!
#2860000
0!
#2880000
b111111 '
b100000000000000000000000000000111111 )
b100000000000000000000000000000111111 ,
b100000000000000000000000000000111111 #
b100000000000000000000000000000111111 (
b111111 *
b111111 -
b111111 1
1!
#2900000
0!
#2920000
b1000000 '
b100000000000000000000000000001000000 )
b100000000000000000000000000001000000 ,
b100000000000000000000000000001000000 #
b100000000000000000000000000001000000 (
b1000000 *
b1000000 -
b1000000 1
1!
#2940000
0!
#2960000
b1000001 '
b100000000000000000000000000001000001 )
b100000000000000000000000000001000001 ,
b100000000000000000000000000001000001 #
b100000000000000000000000000001000001 (
b1000001 *
b1000001 -
b1000001 1
1!
#2980000
0!
#3000000
b1000010 '
b100000000000000000000000000001000010 )
b100000000000000000000000000001000010 ,
b100000000000000000000000000001000010 #
b100000000000000000000000000001000010 (
b1000010 *
b1000010 -
b1000010 1
1!
#3020000
0!
#3040000
b1000011 '
b100000000000000000000000000001000011 )
b100000000000000000000000000001000011 ,
b100000000000000000000000000001000011 #
b100000000000000000000000000001000011 (
b1000011 *
b1000011 -
b1000011 1
1!
#3060000
0!
#3080000
b1000100 '
b100000000000000000000000000001000100 )
b100000000000000000000000000001000100 ,
b100000000000000000000000000001000100 #
b100000000000000000000000000001000100 (
b1000100 *
b1000100 -
b1000100 1
1!
#3100000
0!
#3120000
b1000101 '
b100000000000000000000000000001000101 )
b100000000000000000000000000001000101 ,
b100000000000000000000000000001000101 #
b100000000000000000000000000001000101 (
b1000101 *
b1000101 -
b1000101 1
1!
#3140000
0!
#3160000
b1000110 '
b100000000000000000000000000001000110 )
b100000000000000000000000000001000110 ,
b100000000000000000000000000001000110 #
b100000000000000000000000000001000110 (
b1000110 *
b1000110 -
b1000110 1
1!
#3180000
0!
#3200000
b1000111 '
b100000000000000000000000000001000111 )
b100000000000000000000000000001000111 ,
b100000000000000000000000000001000111 #
b100000000000000000000000000001000111 (
b1000111 *
b1000111 -
b1000111 1
1!
#3220000
0!
#3240000
b1001000 '
b100000000000000000000000000001001000 )
b100000000000000000000000000001001000 ,
b100000000000000000000000000001001000 #
b100000000000000000000000000001001000 (
b1001000 *
b1001000 -
b1001000 1
1!
#3260000
0!
#3280000
b1001001 '
b100000000000000000000000000001001001 )
b100000000000000000000000000001001001 ,
b100000000000000000000000000001001001 #
b100000000000000000000000000001001001 (
b1001001 *
b1001001 -
b1001001 1
1!
#3300000
0!
#3320000
b1001010 '
b100000000000000000000000000001001010 )
b100000000000000000000000000001001010 ,
b100000000000000000000000000001001010 #
b100000000000000000000000000001001010 (
b1001010 *
b1001010 -
b1001010 1
1!
#3340000
0!
#3360000
b1001011 '
b100000000000000000000000000001001011 )
b100000000000000000000000000001001011 ,
b100000000000000000000000000001001011 #
b100000000000000000000000000001001011 (
b1001011 *
b1001011 -
b1001011 1
1!
#3380000
0!
#3400000
b1001100 '
b100000000000000000000000000001001100 )
b100000000000000000000000000001001100 ,
b100000000000000000000000000001001100 #
b100000000000000000000000000001001100 (
b1001100 *
b1001100 -
b1001100 1
1!
#3420000
0!
#3440000
b1001101 '
b100000000000000000000000000001001101 )
b100000000000000000000000000001001101 ,
b100000000000000000000000000001001101 #
b100000000000000000000000000001001101 (
b1001101 *
b1001101 -
b1001101 1
1!
#3460000
0!
#3480000
b1001110 '
b100000000000000000000000000001001110 )
b100000000000000000000000000001001110 ,
b100000000000000000000000000001001110 #
b100000000000000000000000000001001110 (
b1001110 *
b1001110 -
b1001110 1
1!
#3500000
0!
#3520000
b1001111 '
b100000000000000000000000000001001111 )
b100000000000000000000000000001001111 ,
b100000000000000000000000000001001111 #
b100000000000000000000000000001001111 (
b1001111 *
b1001111 -
b1001111 1
1!
#3540000
0!
#3560000
b1010000 '
b100000000000000000000000000001010000 )
b100000000000000000000000000001010000 ,
b100000000000000000000000000001010000 #
b100000000000000000000000000001010000 (
b1010000 *
b1010000 -
b1010000 1
1!
#3580000
0!
#3600000
b1010001 '
b100000000000000000000000000001010001 )
b100000000000000000000000000001010001 ,
b100000000000000000000000000001010001 #
b100000000000000000000000000001010001 (
b1010001 *
b1010001 -
b1010001 1
1!
#3620000
0!
#3640000
b1010010 '
b100000000000000000000000000001010010 )
b100000000000000000000000000001010010 ,
b100000000000000000000000000001010010 #
b100000000000000000000000000001010010 (
b1010010 *
b1010010 -
b1010010 1
1!
#3660000
0!
#3680000
b1010011 '
b100000000000000000000000000001010011 )
b100000000000000000000000000001010011 ,
b100000000000000000000000000001010011 #
b100000000000000000000000000001010011 (
b1010011 *
b1010011 -
b1010011 1
1!
#3700000
0!
#3720000
b1010100 '
b100000000000000000000000000001010100 )
b100000000000000000000000000001010100 ,
b100000000000000000000000000001010100 #
b100000000000000000000000000001010100 (
b1010100 *
b1010100 -
b1010100 1
1!
#3740000
0!
#3760000
b1010101 '
b100000000000000000000000000001010101 )
b100000000000000000000000000001010101 ,
b100000000000000000000000000001010101 #
b100000000000000000000000000001010101 (
b1010101 *
b1010101 -
b1010101 1
1!
#3780000
0!
#3800000
b1010110 '
b100000000000000000000000000001010110 )
b100000000000000000000000000001010110 ,
b100000000000000000000000000001010110 #
b100000000000000000000000000001010110 (
b1010110 *
b1010110 -
b1010110 1
1!
#3820000
0!
#3840000
b1010111 '
b100000000000000000000000000001010111 )
b100000000000000000000000000001010111 ,
b100000000000000000000000000001010111 #
b100000000000000000000000000001010111 (
b1010111 *
b1010111 -
b1010111 1
1!
#3860000
0!
#3880000
b1011000 '
b100000000000000000000000000001011000 )
b100000000000000000000000000001011000 ,
b100000000000000000000000000001011000 #
b100000000000000000000000000001011000 (
b1011000 *
b1011000 -
b1011000 1
1!
#3900000
0!
#3920000
b1011001 '
b100000000000000000000000000001011001 )
b100000000000000000000000000001011001 ,
b100000000000000000000000000001011001 #
b100000000000000000000000000001011001 (
b1011001 *
b1011001 -
b1011001 1
1!
#3940000
0!
#3960000
b1011010 '
b100000000000000000000000000001011010 )
b100000000000000000000000000001011010 ,
b100000000000000000000000000001011010 #
b100000000000000000000000000001011010 (
b1011010 *
b1011010 -
b1011010 1
1!
#3980000
0!
#4000000
b1011011 '
b100000000000000000000000000001011011 )
b100000000000000000000000000001011011 ,
b100000000000000000000000000001011011 #
b100000000000000000000000000001011011 (
b1011011 *
b1011011 -
b1011011 1
1!
#4020000
0!
#4040000
b1011100 '
b100000000000000000000000000001011100 )
b100000000000000000000000000001011100 ,
b100000000000000000000000000001011100 #
b100000000000000000000000000001011100 (
b1011100 *
b1011100 -
b1011100 1
1!
#4060000
0!
#4080000
b1011101 '
b100000000000000000000000000001011101 )
b100000000000000000000000000001011101 ,
b100000000000000000000000000001011101 #
b100000000000000000000000000001011101 (
b1011101 *
b1011101 -
b1011101 1
1!
#4100000
0!
#4120000
b1011110 '
b100000000000000000000000000001011110 )
b100000000000000000000000000001011110 ,
b100000000000000000000000000001011110 #
b100000000000000000000000000001011110 (
b1011110 *
b1011110 -
b1011110 1
1!
#4140000
0!
#4160000
b1011111 '
b100000000000000000000000000001011111 )
b100000000000000000000000000001011111 ,
b100000000000000000000000000001011111 #
b100000000000000000000000000001011111 (
b1011111 *
b1011111 -
b1011111 1
1!
#4180000
0!
#4200000
b1100000 '
b100000000000000000000000000001100000 )
b100000000000000000000000000001100000 ,
b100000000000000000000000000001100000 #
b100000000000000000000000000001100000 (
b1100000 *
b1100000 -
b1100000 1
1!
#4220000
0!
#4240000
b1100001 '
b100000000000000000000000000001100001 )
b100000000000000000000000000001100001 ,
b100000000000000000000000000001100001 #
b100000000000000000000000000001100001 (
b1100001 *
b1100001 -
b1100001 1
1!
#4260000
0!
#4280000
b1100010 '
b100000000000000000000000000001100010 )
b100000000000000000000000000001100010 ,
b100000000000000000000000000001100010 #
b100000000000000000000000000001100010 (
b1100010 *
b1100010 -
b1100010 1
1!
#4300000
0!
#4320000
b1100011 '
b100000000000000000000000000001100011 )
b100000000000000000000000000001100011 ,
b100000000000000000000000000001100011 #
b100000000000000000000000000001100011 (
b1100011 *
b1100011 -
b1100011 1
1!
#4340000
0!
#4360000
b1100100 '
b100000000000000000000000000001100100 )
b100000000000000000000000000001100100 ,
b100000000000000000000000000001100100 #
b100000000000000000000000000001100100 (
b1100100 *
b1100100 -
b1100100 1
1!
#4380000
0!
#4400000
b1100101 '
b100000000000000000000000000001100101 )
b100000000000000000000000000001100101 ,
b100000000000000000000000000001100101 #
b100000000000000000000000000001100101 (
b1100101 *
b1100101 -
b1100101 1
1!
#4420000
0!
#4440000
b1100110 '
b100000000000000000000000000001100110 )
b100000000000000000000000000001100110 ,
b100000000000000000000000000001100110 #
b100000000000000000000000000001100110 (
b1100110 *
b1100110 -
b1100110 1
1!
#4460000
0!
#4480000
b1100111 '
b100000000000000000000000000001100111 )
b100000000000000000000000000001100111 ,
b100000000000000000000000000001100111 #
b100000000000000000000000000001100111 (
b1100111 *
b1100111 -
b1100111 1
1!
#4500000
0!
#4520000
b1101000 '
b100000000000000000000000000001101000 )
b100000000000000000000000000001101000 ,
b100000000000000000000000000001101000 #
b100000000000000000000000000001101000 (
b1101000 *
b1101000 -
b1101000 1
1!
#4540000
0!
#4560000
b1101001 '
b100000000000000000000000000001101001 )
b100000000000000000000000000001101001 ,
b100000000000000000000000000001101001 #
b100000000000000000000000000001101001 (
b1101001 *
b1101001 -
b1101001 1
1!
#4580000
0!
#4600000
b1101010 '
b100000000000000000000000000001101010 )
b100000000000000000000000000001101010 ,
b100000000000000000000000000001101010 #
b100000000000000000000000000001101010 (
b1101010 *
b1101010 -
b1101010 1
1!
#4620000
0!
#4640000
b1101011 '
b100000000000000000000000000001101011 )
b100000000000000000000000000001101011 ,
b100000000000000000000000000001101011 #
b100000000000000000000000000001101011 (
b1101011 *
b1101011 -
b1101011 1
1!
#4660000
0!
#4680000
b1101100 '
b100000000000000000000000000001101100 )
b100000000000000000000000000001101100 ,
b100000000000000000000000000001101100 #
b100000000000000000000000000001101100 (
b1101100 *
b1101100 -
b1101100 1
1!
#4700000
0!
#4720000
b1101101 '
b100000000000000000000000000001101101 )
b100000000000000000000000000001101101 ,
b100000000000000000000000000001101101 #
b100000000000000000000000000001101101 (
b1101101 *
b1101101 -
b1101101 1
1!
#4740000
0!
#4760000
b1101110 '
b100000000000000000000000000001101110 )
b100000000000000000000000000001101110 ,
b100000000000000000000000000001101110 #
b100000000000000000000000000001101110 (
b1101110 *
b1101110 -
b1101110 1
1!
#4780000
0!
#4800000
b1101111 '
b100000000000000000000000000001101111 )
b100000000000000000000000000001101111 ,
b100000000000000000000000000001101111 #
b100000000000000000000000000001101111 (
b1101111 *
b1101111 -
b1101111 1
1!
#4820000
0!
#4840000
b1110000 '
b100000000000000000000000000001110000 )
b100000000000000000000000000001110000 ,
b100000000000000000000000000001110000 #
b100000000000000000000000000001110000 (
b1110000 *
b1110000 -
b1110000 1
1!
#4860000
0!
#4880000
b1110001 '
b100000000000000000000000000001110001 )
b100000000000000000000000000001110001 ,
b100000000000000000000000000001110001 #
b100000000000000000000000000001110001 (
b1110001 *
b1110001 -
b1110001 1
1!
#4900000
0!
#4920000
b1110010 '
b100000000000000000000000000001110010 )
b100000000000000000000000000001110010 ,
b100000000000000000000000000001110010 #
b100000000000000000000000000001110010 (
b1110010 *
b1110010 -
b1110010 1
1!
#4940000
0!
